LICENSE
verbformen_cli/.gitignore
verbformen_cli/__init__.py
verbformen_cli/cli.py
verbformen_cli/clients.py
verbformen_cli/display.py
verbformen_cli/downloaders.py
verbformen_cli/models.py
verbformen_cli/parsers.py
verbformen_cli/settings.py
verbformen_cli-0.2.3.dist-info/entry_points.txt
verbformen_cli-0.2.3.dist-info/LICENSE
verbformen_cli-0.2.3.dist-info/WHEEL
verbformen_cli-0.2.3.dist-info/METADATA
verbformen_cli-0.2.3.dist-info/RECORD
