Metadata-Version: 2.1
Name: verbformen-cli
Version: 0.2.3
Summary: Verbformen CLI
Home-page: https://github.com/millern/verbformen-cli
Author: Nicholas Miller
Author-email: njmiller6@gmail.com
Requires-Python: >=3.9,<4.0
Classifier: Programming Language :: Python :: 3
Classifier: Programming Language :: Python :: 3.9
Requires-Dist: beautifulsoup4 (>=4.9.3,<5.0.0)
Requires-Dist: click (>=7.0,<8.0)
Requires-Dist: loguru (>=0.5.3,<0.6.0)
Requires-Dist: pydantic (>=1.8.2,<2.0.0)
Requires-Dist: requests (>=2.26.0,<3.0.0)
Requires-Dist: rich (>=10.7.0,<11.0.0)
Requires-Dist: xextract (>=0.1.8,<0.2.0)
Project-URL: Repository, https://github.com/millern/verbformen-cli
